[
  {
    "id": 1,
    "title": "Shop Floor Rush Order — Meridian Medical",
    "content": "J-1055 is a rush order. All hands prioritize. Delivery commitment: Friday 4pm. Questions to Morgan.",
    "severity": "Warning",
    "scope": "CompanyWide",
    "requiresAcknowledgment": true,
    "expiresAt": "2026-04-25T00:00:00Z",
    "isSystemGenerated": false,
    "systemSource": null,
    "createdById": 1,
    "createdByName": "Hayes, Morgan",
    "createdAt": "2026-04-19T08:00:00Z",
    "acknowledgmentCount": 4,
    "targetUserCount": 7,
    "isAcknowledgedByCurrentUser": true,
    "targetTeamIds": []
  },
  {
    "id": 2,
    "title": "New Expense Policy Effective May 1",
    "content": "Starting May 1, meals over $50 require pre-approval. Full policy in the handbook.",
    "severity": "Info",
    "scope": "CompanyWide",
    "requiresAcknowledgment": true,
    "expiresAt": null,
    "isSystemGenerated": false,
    "systemSource": null,
    "createdById": 1,
    "createdByName": "Hayes, Morgan",
    "createdAt": "2026-04-17T13:30:00Z",
    "acknowledgmentCount": 5,
    "targetUserCount": 7,
    "isAcknowledgedByCurrentUser": true,
    "targetTeamIds": []
  },
  {
    "id": 3,
    "title": "Air Compressor PM Scheduled Saturday",
    "content": "Atlas Copco GA-55 will be offline Saturday 6am–10am for preventive maintenance. Plan around air-tool needs.",
    "severity": "Info",
    "scope": "CompanyWide",
    "requiresAcknowledgment": false,
    "expiresAt": "2026-04-27T00:00:00Z",
    "isSystemGenerated": false,
    "systemSource": null,
    "createdById": 1,
    "createdByName": "Hayes, Morgan",
    "createdAt": "2026-04-21T15:20:00Z",
    "acknowledgmentCount": 0,
    "targetUserCount": 7,
    "isAcknowledgedByCurrentUser": false,
    "targetTeamIds": []
  },
  {
    "id": 4,
    "title": "Low Stock — Cutting Fluid",
    "content": "Cutting fluid stock is below reorder point. Auto-PO submitted to Grainger. ETA Thursday.",
    "severity": "Warning",
    "scope": "Department",
    "requiresAcknowledgment": false,
    "expiresAt": "2026-04-26T00:00:00Z",
    "isSystemGenerated": true,
    "systemSource": "InventoryReorderJob",
    "createdById": 1,
    "createdByName": "System",
    "createdAt": "2026-04-22T06:00:00Z",
    "acknowledgmentCount": 0,
    "targetUserCount": 3,
    "isAcknowledgedByCurrentUser": false,
    "targetTeamIds": []
  },
  {
    "id": 5,
    "title": "Fire Drill — Thursday 2pm",
    "content": "Full facility fire drill this Thursday at 2pm sharp. Muster at south parking lot.",
    "severity": "Critical",
    "scope": "CompanyWide",
    "requiresAcknowledgment": true,
    "expiresAt": "2026-04-23T20:00:00Z",
    "isSystemGenerated": false,
    "systemSource": null,
    "createdById": 1,
    "createdByName": "Hayes, Morgan",
    "createdAt": "2026-04-22T11:00:00Z",
    "acknowledgmentCount": 3,
    "targetUserCount": 7,
    "isAcknowledgedByCurrentUser": true,
    "targetTeamIds": []
  }
]
